{
  "name": "commit",
  "description": "Create a git commit.\n\n**Examples:**\n- Commit staged files: `{\"message\": \"Fix bug in parser\"}`\n- Stage and commit all: `{\"message\": \"Update docs\", \"add_all\": true}`\n\n**Note:** Files must be staged first unless using `add_all: true`.",
  "inputSchema": {
    "type": "object",
    "properties": {
      "message": {
        "type": "string",
        "description": "Commit message"
      },
      "add_all": {
        "type": "boolean",
        "description": "Stage all changes first"
      }
    },
    "required": ["message"]
  }
}
